coverage_conditional_plugin/__init__.py
coverage_conditional_plugin/py.typed
coverage_conditional_plugin/version.py
coverage_conditional_plugin-0.8.0.dist-info/LICENSE
coverage_conditional_plugin-0.8.0.dist-info/WHEEL
coverage_conditional_plugin-0.8.0.dist-info/METADATA
coverage_conditional_plugin-0.8.0.dist-info/RECORD
