Metadata-Version: 2.1
Name: coverage-conditional-plugin
Version: 0.8.0
Summary: Conditional coverage based on any rules you define!
Home-page: https://github.com/wemake-services/coverage-conditional-plugin
License: MIT
Keywords: coverage,coverage.py,pytest-cov,testing
Author: sobolevn
Author-email: mail@sobolevn.me
Requires-Python: >=3.7,<4.0
Classifier: Development Status :: 4 - Beta
Classifier: Intended Audience :: Developers
Classifier: License :: OSI Approved :: MIT License
Classifier: Operating System :: OS Independent
Classifier: Programming Language :: Python :: 3
Classifier: Programming Language :: Python :: 3.7
Classifier: Programming Language :: Python :: 3.8
Classifier: Programming Language :: Python :: 3.9
Classifier: Programming Language :: Python :: 3.10
Classifier: Topic :: Software Development :: Libraries :: Python Modules
Requires-Dist: coverage (>=5,<8)
Requires-Dist: importlib_metadata; python_version < "3.10"
Requires-Dist: packaging (>=20.4)
Project-URL: Funding, https://github.com/sponsors/wemake-services
Project-URL: Repository, https://github.com/wemake-services/coverage-conditional-plugin
